{
  "project_info": {
    "project_number": "349680331672",
    "project_id": "teste23-d1003",
    "storage_bucket": "teste23-d1003.firebasestorage.app"
  },
  "client": [
    {
      "client_info": {
        "mobilesdk_app_id": "1:349680331672:android:4bc82a628d6b508764d9ed",
        "android_client_info": {
          "package_name": "com.krxlabs.cxlus"
        }
      },
      "oauth_client": [],
      "api_key": [
        {
          "current_key": "AIzaSyB3B2kZlIuPwa5kAgGZ3mG6hT4kW2Y2Nig"
        }
      ],
      "services": {
        "appinvite_service": {
          "other_platform_oauth_client": []
        }
      }
    }
  ],
  "configuration_version": "1"
}